[
  {
    "PARTICLE_EFFECTS": {
      "THREE":[

        {
          "id":"test_effect",
          "data":{
            "system_key":"THREE",
            "renderer_id":"gpu_additive_atlas_renderer",
            "particle_id":"default",
            "count":2,
            "simulation_id":"gpu_predictive_simulation"
          }
        },
        {
          "id":"shockwave_hit_effect",
          "data":{
            "system_key":"THREE",
            "renderer_id":"gpu_additive_atlas_renderer",
            "particle_id":"shockwave_hit_particles",
            "count":1,
            "simulation_id":"gpu_predictive_simulation"
          }
        },
        {
          "id":"implosion_shockwave_hit",
          "data":{
            "system_key":"THREE",
            "renderer_id":"gpu_additive_atlas_renderer",
            "particle_id":"implosion_shockwave_hit_particles",
            "count":1,
            "simulation_id":"gpu_predictive_simulation"
          }
        },
        {
          "id":"explosion_smoke_plume",
          "data":{
            "system_key":"THREE",
            "renderer_id":"gpu_normal_atlas_renderer",
            "particle_id":"explosion_smoke_plume_particles",
            "count":5,
            "simulation_id":"gpu_predictive_simulation"
          }
        },
        {
          "id":"module_volume_dust_puff_effect",
          "data":{
            "system_key":"THREE",
            "renderer_id":"gpu_normal_atlas_renderer",
            "particle_id":"quick_near_dust_particle",
            "count":3,
            "simulation_id":"gpu_predictive_simulation"
          }
        },
        {
          "id":"vehicle_burn_smoke_effect",
          "data":{
            "system_key":"THREE",
            "renderer_id":"gpu_normal_atlas_renderer",
            "particle_id":"vehicle_burn_smoke_particles",
            "count":2,
            "simulation_id":"gpu_predictive_simulation"
          }
        },
        {
          "id":"hit_sparks_effect",
          "data":{
            "system_key":"THREE",
            "renderer_id":"gpu_additive_atlas_renderer",
            "particle_id":"sparks_hit_particles",
            "count":1,
            "simulation_id":"gpu_predictive_simulation"
          }
        },        {
          "id":"vehicle_fire_effect",
          "data":{
            "system_key":"THREE",
            "renderer_id":"gpu_additive_atlas_renderer",
            "particle_id":"vehicle_fire_particles",
            "count":2,
            "simulation_id":"gpu_predictive_simulation"
          }
        },
        {
          "id":"fx_cannon_muzzle_flame",
          "data":{
            "system_key":"THREE",
            "renderer_id":"gpu_additive_atlas_renderer",
            "particle_id":"cannon_muzzle_flame_particles",
            "count":3,
            "simulation_id":"gpu_predictive_simulation"
          }
        },        {
          "id":"firey_explosion_core",
          "data":{
            "system_key":"THREE",
            "renderer_id":"gpu_additive_atlas_renderer",
            "particle_id":"firey_explosion_core_particles",
            "count":20,
            "simulation_id":"gpu_predictive_simulation"
          }
        },
        {
          "id":"normal_explosion_core",
          "data":{
            "system_key":"THREE",
            "renderer_id":"gpu_normal_atlas_renderer",
            "particle_id":"firey_explosion_core_particles",
            "count":3,
            "simulation_id":"gpu_predictive_simulation"
          }
        },
        {
          "id":"big_shockwave_hit",
          "data":{
            "system_key":"THREE",
            "renderer_id":"gpu_additive_atlas_renderer",
            "particle_id":"big_shockwave_hit_particles",
            "count":1,
            "simulation_id":"gpu_predictive_simulation"
          }
        },

        {
          "id":"muzzle_shockwave_flash",
          "data":{
            "system_key":"THREE",
            "renderer_id":"gpu_additive_atlas_renderer",
            "particle_id":"muzzle_shockwave_flash_particles",
            "count":1,
            "simulation_id":"gpu_predictive_simulation"
          }
        },

        {
          "id":"muzzle_pulse_flash",
          "data":{
            "system_key":"THREE",
            "renderer_id":"gpu_additive_atlas_renderer",
            "particle_id":"muzzle_pulse_flash_particles",
            "count":1,
            "simulation_id":"gpu_predictive_simulation"
          }
        },
        {
          "id":"machine_gun_trail_effect",
          "data":{
            "system_key":"THREE",
            "renderer_id":"gpu_additive_atlas_trail_renderer",
            "particle_id":"machine_gun_trail_effect_particle",
            "count":1,
            "simulation_id":"gpu_predictive_simulation"
          }
        },        {
          "id":"cannon_20mm_trail_effect",
          "data":{
            "system_key":"THREE",
            "renderer_id":"gpu_additive_atlas_trail_renderer",
            "particle_id":"cannon_20mm_trail_effect_particle",
            "count":1,
            "simulation_id":"gpu_predictive_simulation"
          }
        },
        {
          "id":"cannon_trail_effect",
          "data":{
            "system_key":"THREE",
            "renderer_id":"gpu_additive_atlas_trail_renderer",
            "particle_id":"cannon_trail_effect_particle",
            "count":1,
            "simulation_id":"gpu_predictive_simulation"
          }
        },

        {
          "id":"big_sparkly_shatter",
          "data":{
            "system_key":"THREE",
            "renderer_id":"gpu_additive_atlas_renderer",
            "particle_id":"big_sparkly_shatter_particles",
            "count":15,
            "simulation_id":"gpu_predictive_simulation"
          }
        },

        {
          "id":"swirly_module_effect",
          "data":{
            "system_key":"THREE",
            "renderer_id":"gpu_additive_atlas_renderer",
            "particle_id":"swirly_module_effect_particles",
            "count":2,
            "simulation_id":"gpu_predictive_simulation"
          }
        },

        {
          "id":"shield_module_sphere_effect",
          "data":{
            "system_key":"THREE",
            "renderer_id":"gpu_additive_atlas_renderer",
            "particle_id":"shield_sphere_effect_particles",
            "count":4,
            "simulation_id":"gpu_predictive_simulation"
          }
        },

        {
          "id":"shield_module_edge_effect",
          "data":{
            "system_key":"THREE",
            "renderer_id":"gpu_additive_atlas_renderer",
            "particle_id":"shield_edge_effect_particles",
            "count":4,
            "simulation_id":"gpu_predictive_simulation"
          }
        },

        {
          "id":"shield_module_sparks_effect",
          "data":{
            "system_key":"THREE",
            "renderer_id":"gpu_additive_atlas_renderer",
            "particle_id":"shield_spark_stars_particles",
            "count":10,
            "simulation_id":"gpu_predictive_simulation"
          }
        },

        {
          "id":"thruster_smoke_effect",
          "data":{
            "system_key":"THREE",
            "renderer_id":"gpu_additive_atlas_renderer",
            "particle_id":"thruster_smoke_particles",
            "count":2,
            "simulation_id":"gpu_predictive_simulation"
          }
        },

        {
          "id":"thruster_flame_effect",
          "data":{
            "system_key":"THREE",
            "renderer_id":"gpu_additive_atlas_renderer",
            "particle_id":"thruster_flame_particles",
            "count":25,
            "simulation_id":"gpu_predictive_simulation"
          }
        },

        {
          "id":"turbine_effect",
          "data":{
            "system_key":"THREE",
            "renderer_id":"gpu_additive_atlas_renderer",
            "particle_id":"turbine_particles",
            "count":35,
            "simulation_id":"gpu_predictive_simulation"
          }
        },

        {
          "id":"hyper_module_sparks_effect",
          "data":{
            "system_key":"THREE",
            "renderer_id":"gpu_additive_atlas_renderer",
            "particle_id":"hyper_spark_stars_particles",
            "count":25,
            "simulation_id":"gpu_predictive_simulation"
          }
        },

        {
          "id":"flare_dot_light_effect",
          "data":{
            "system_key":"THREE",
            "renderer_id":"gpu_additive_atlas_renderer",
            "particle_id":"flare_dot_light_particles",
            "count":1,
            "simulation_id":"gpu_predictive_simulation"
          }
        },

        {
          "id":"flare_dot_module_effect",
          "data":{
            "system_key":"THREE",
            "renderer_id":"gpu_additive_atlas_renderer",
            "particle_id":"flare_dot_effect_particles",
            "count":5,
            "simulation_id":"gpu_predictive_simulation"
          }
        },

        {
          "id":"track_ground_module_effect",
          "data":{
            "system_key":"THREE",
            "renderer_id":"gpu_opaque_atlas_renderer",
            "particle_id":"track_ground_effect_particles",
            "count":1,
            "simulation_id":"gpu_predictive_simulation"
          }
        },



        {
          "id":"sparkly_stars_effect",
          "data":{
            "system_key":"THREE",
            "renderer_id":"gpu_additive_atlas_renderer",
            "particle_id":"sparkly_stars_particles",
            "count":8,
            "simulation_id":"gpu_predictive_simulation"
          }
        },

        {
          "id":"falling_leaf_effect",
          "data":{
            "system_key":"THREE",
            "renderer_id":"gpu_opaque_atlas_renderer",
            "particle_id":"falling_leaf_particles",
            "count":5,
            "simulation_id":"gpu_predictive_simulation"
          }
        },

        {
          "id":"big_leafy_swirl",
          "data":{
            "system_key":"THREE",
            "renderer_id":"gpu_opaque_atlas_renderer",
            "particle_id":"big_leafy_swirl_particles",
            "count":8,
            "simulation_id":"gpu_predictive_simulation"
          }
        },

        {
          "id":"bright_little_sparks",
          "data":{
            "system_key":"THREE",
            "renderer_id":"gpu_additive_atlas_renderer",
            "particle_id":"bright_little_sparks_particles",
            "count":8,
            "simulation_id":"gpu_predictive_simulation"
          }
        },

        {
          "id":"ground_mud_spray",
          "data":{
            "system_key":"THREE",
            "renderer_id":"gpu_opaque_atlas_renderer",
            "particle_id":"muddy_ground_spray_particles",
            "count":2,
            "simulation_id":"gpu_predictive_simulation"
          }
        },
        {
          "id":"leafy_ground_spray",
          "data":{
            "system_key":"THREE",
            "renderer_id":"gpu_opaque_atlas_renderer",
            "particle_id":"leafy_ground_spray_particles",
            "count":2,
            "simulation_id":"gpu_predictive_simulation"
          }
        },
        {
          "id":"engine_throttle_smoke",
          "data":{
            "system_key":"THREE",
            "renderer_id":"gpu_normal_atlas_renderer",
            "particle_id":"grey_smoke",
            "count":1,
            "simulation_id":"gpu_predictive_simulation"
          }
        },
        {
          "id":"condensation_trail",
          "data":{
            "system_key":"THREE",
            "renderer_id":"gpu_transparent_atlas_renderer",
            "particle_id":"condensation_particle",
            "count":6,
            "simulation_id":"gpu_predictive_simulation"
          }
        },
        {
          "id":"condensation_near_effect",
          "data":{
            "system_key":"THREE",
            "renderer_id":"gpu_transparent_atlas_renderer",
            "particle_id":"condensation_near_particle",
            "count":3,
            "simulation_id":"gpu_predictive_simulation"
          }
        },
        {
          "id":"water_spray_particle_effect",
          "data":{
            "system_key":"THREE",
            "renderer_id":"gpu_normal_atlas_renderer",
            "particle_id":"water_spray_particles",
            "count":1,
            "simulation_id":"gpu_predictive_simulation"
          }
        },
        {
          "id":"water_wake_particle_effect",
          "data":{
            "system_key":"THREE",
            "renderer_id":"gpu_opaque_stamp_renderer",
            "particle_id":"water_wake_particles",
            "count":1,
            "simulation_id":"gpu_stamp_simulation"
          }
        },
        {
          "id":"engine_near_smoke",
          "data":{
            "system_key":"THREE",
            "renderer_id":"gpu_normal_atlas_renderer",
            "particle_id":"quick_near_smoke_particle",
            "count":1,
            "simulation_id":"gpu_predictive_simulation"
          }
        },


        {
          "id":"ground_dirt_clob_effect",
          "data":{
            "system_key":"THREE",
            "renderer_id":"gpu_opaque_stamp_renderer",
            "particle_id":"ground_dirt_clob_particle",
            "count":1,
            "simulation_id":"gpu_stamp_simulation"
          }
        },

        {
          "id":"water_foam_particle_effect",
          "data":{
            "system_key":"THREE",
            "renderer_id":"gpu_opaque_stamp_renderer",
            "particle_id":"water_foam_particles",
            "count":1,
            "simulation_id":"gpu_stamp_simulation"
          }
        },
        {
          "id":"water_shade_particle_effect",
          "data":{
            "system_key":"THREE",
            "renderer_id":"gpu_opaque_stamp_renderer",
            "particle_id":"water_shade_particles",
            "count":1,
            "simulation_id":"gpu_stamp_simulation"
          }
        },
        {
          "id":"track_ground_dark_module_effect",
          "data":{
            "system_key":"THREE",
            "renderer_id":"gpu_opaque_stamp_renderer",
            "particle_id":"ground_dirt_dark_clob_particle",
            "count":1,
            "simulation_id":"gpu_stamp_simulation"
          }
        }

      ]
    }
  }
]
