[{
  "DYNAMIC_SCENARIOS":{

    "GAME_SCENARIOS":[
      {
        "id": "test_data",
        "data": [
          {
            "data_key":"dynamic_view_init",
            "config": {
            }
          }
        ]
      },
      {
        "id": "home_hovel_dynamic",
        "data": [
          {
            "data_key":"dynamic_view_init",
            "config": {
              "camera": {
                "mode": "follow_cam_main_char",
                "offset_pos": [1, 6, -11],
                "offset_lookAt": [0, 2.5, 0]
              },
              "gui_page":"page_scene_home",
              "environment": "sunny_day",
              "player": {
                "pos": [-0.9, 0, -0.4],
                "rot": [0, -0.911, 0]
              },
              "grid": {
                "entrance_tile": [7, 15],
                "start_tile": [7, 10],
                "dataId":"grid_home_hovel",
                "rot": [0, 0.19, 0],
                "pos": [-2.4, 0, -1.1]
              },
              "characters": [
                {
                  "character":"HOME_DUDE",
                  "pos": [-2.8, 0, 0.1],
                  "rot": [0, -1.111, 0]
                },
                {
                  "character":"COMPANION_ONE",
                  "pos": [0.4, 0, 0.2],
                  "rot": [0, 0.611, 0]
                }
              ],
              "spawn":[
                {"piece": "NINJASWORD",
                  "pos": [-0.45, 0.6, 1.2],
                  "rot": [ 1.711, 0, 1]
                },
                {"piece": "HELMET_VIKING",
                  "pos": [-0.35, 0, 1.5],
                  "rot": [-1.911,0,  0]
                }
              ]
            }
          }
        ]
      }
    ]
  }
}]